sparkwheel/__init__.py
sparkwheel/coercion.py
sparkwheel/config.py
sparkwheel/errors/__init__.py
sparkwheel/errors/context.py
sparkwheel/errors/formatters.py
sparkwheel/errors/suggestions.py
sparkwheel/items.py
sparkwheel/loader.py
sparkwheel/metadata.py
sparkwheel/operators.py
sparkwheel/parser.py
sparkwheel/path_patterns.py
sparkwheel/path_utils.py
sparkwheel/preprocessor.py
sparkwheel/resolver.py
sparkwheel/schema.py
sparkwheel/utils/__init__.py
sparkwheel/utils/constants.py
sparkwheel/utils/enums.py
sparkwheel/utils/exceptions.py
sparkwheel/utils/misc.py
sparkwheel/utils/module.py
sparkwheel/utils/types.py
sparkwheel-0.0.6.dist-info/WHEEL
sparkwheel-0.0.6.dist-info/METADATA
sparkwheel-0.0.6.dist-info/RECORD
