Metadata-Version: 2.4
Name: sparkwheel
Version: 0.0.6
Summary: A powerful YAML-based configuration system with references, expressions, and dynamic instantiation
Keywords: configuration,yaml,config,deep-learning,machine-learning
Author: Project Lighter
Author-email: Project Lighter <noreply@lighter.com>
License-Expression: Apache-2.0
Classifier: Development Status :: 3 - Alpha
Classifier: Intended Audience :: Developers
Classifier: Intended Audience :: Science/Research
Classifier: Operating System :: OS Independent
Classifier: Topic :: Software Development :: Libraries :: Python Modules
Classifier: License :: OSI Approved :: Apache Software License
Classifier: Programming Language :: Python :: 3
Classifier: Programming Language :: Python :: 3.10
Classifier: Programming Language :: Python :: 3.11
Classifier: Programming Language :: Python :: 3.12
Classifier: Topic :: Scientific/Engineering :: Artificial Intelligence
Requires-Dist: pyyaml>=6.0
Requires-Python: >=3.10
Project-URL: Documentation, https://project-lighter.github.io/sparkwheel
Project-URL: Homepage, https://github.com/project-lighter/sparkwheel
Project-URL: Issues, https://github.com/project-lighter/sparkwheel/issues
Project-URL: Repository, https://github.com/project-lighter/sparkwheel
